{"asset": {                "version": "0.0",                "gltfUpAxis": "Y"            },            "geometricError":100.000000,"root": {                "transform": [-0.918552,-0.395300,0.000000,0.000000,0.154584,-0.359205,0.920367,0.000000,-0.363446,0.844532,0.393284,0.000000,-2319306.954791,5389332.801610,2492921.006692,1],                "boundingVolume": {                    "region": [1.977141,0.404167,1.977241,0.404235,0.000000,4.000000]},"geometricError": 100.000000,                        "refine": "REPLACE",                        "content": {                            "uri": "./tile/3/5/7.b3dm"}}}