{"asset": {                "version": "0.0",                "gltfUpAxis": "Y"            },            "geometricError":100.000000,"root": {                "transform": [-0.918695,-0.394968,0.000000,0.000000,0.154202,-0.358674,0.920638,0.000000,-0.363248,0.844915,0.392644,0.000000,-2318044.103689,5391767.891625,2488854.158422,1],                "boundingVolume": {                    "region": [1.976780,0.403464,1.976879,0.403544,0.000000,43.000000]},"geometricError": 100.000000,                        "refine": "REPLACE",                        "content": {                            "uri": "./tile/3/1/0.b3dm"}}}